pymazebuilder/__init__.py
pymazebuilder/cell.py
pymazebuilder/grid.py
pymazebuilder/main.py
pymazebuilder/renderer.py
pymazebuilder/test.py
pymazebuilder/utils.py
pymazebuilder/generators/__init__.py
pymazebuilder/generators/dungeon.py
pymazebuilder/generators/generator.py
pymazebuilder/generators/generator_manager.py
pymazebuilder/generators/maze.py
pymazebuilder/generators/room.py
pymazebuilder/generators/stairs.py
pymazebuilder-1.4.6.dist-info/licenses/LICENSE
pymazebuilder-1.4.6.dist-info/METADATA
pymazebuilder-1.4.6.dist-info/WHEEL
pymazebuilder-1.4.6.dist-info/entry_points.txt
pymazebuilder-1.4.6.dist-info/top_level.txt
pymazebuilder-1.4.6.dist-info/RECORD
