Metadata-Version: 2.4
Name: pymazebuilder
Version: 1.4.6
Summary: Generate mazes and dungeons for RPG games
Home-page: https://github.com/w4ffl35/PyMazeBuilder
Author: w4ffl35
Author-email: contact@capsizegames.com
License: Apache-2.0
Keywords: maze,builder,generator,rpg,game,development
License-File: LICENSE
Dynamic: author
Dynamic: author-email
Dynamic: description
Dynamic: description-content-type
Dynamic: home-page
Dynamic: keywords
Dynamic: license
Dynamic: license-file
Dynamic: summary
